ttlecs/__init__.py
ttlecs/cmd.py
ttlecs/config_template.py
ttlecs/core/__init__.py
ttlecs/core/context.py
ttlecs/provider/__init__.py
ttlecs/provider/aliyun.py
ttlecs/utils/__init__.py
ttlecs/utils/random_util.py
ttlecs-0.1.4.dist-info/LICENSE
ttlecs-0.1.4.dist-info/METADATA
ttlecs-0.1.4.dist-info/WHEEL
ttlecs-0.1.4.dist-info/entry_points.txt
ttlecs-0.1.4.dist-info/top_level.txt
ttlecs-0.1.4.dist-info/RECORD
